textnormx/__init__.py
textnormx/cleaner/__init__.py
textnormx/cleaner/mappings.py
textnormx/cleaner/normalize.py
textnormx/parser/__init__.py
textnormx/parser/chunk.py
textnormx/parser/html.py
textnormx/parser/markdown.py
textnormx/parser/types.py
textnormx-0.2.1.dist-info/METADATA
textnormx-0.2.1.dist-info/WHEEL
textnormx-0.2.1.dist-info/entry_points.txt
textnormx-0.2.1.dist-info/RECORD
