Metadata-Version: 2.4
Name: textnormx
Version: 0.2.1
Summary: Normalize/clean text from PDF OCR/extraction (PUA bullets, quotes, dashes, NBSP, control chars)
Project-URL: Homepage, https://example.com
Author-email: Vous <you@example.com>
License: MIT
Requires-Python: >=3.8
Requires-Dist: wordfreq<4.0.0,>=3.1.1
Provides-Extra: html
Requires-Dist: beautifulsoup4>=4.9; extra == 'html'
